pikaraoke/CHANGELOG.md
pikaraoke/_TRANSLATION.md
pikaraoke/__init__.py
pikaraoke/app.py
pikaraoke/babel.cfg
pikaraoke/constants.py
pikaraoke/karaoke.py
pikaraoke/messages.pot
pikaraoke/version.py
pikaraoke/lib/args.py
pikaraoke/lib/browser.py
pikaraoke/lib/current_app.py
pikaraoke/lib/download_manager.py
pikaraoke/lib/ffmpeg.py
pikaraoke/lib/file_resolver.py
pikaraoke/lib/get_platform.py
pikaraoke/lib/network.py
pikaraoke/lib/omxclient.py
pikaraoke/lib/queue_manager.py
pikaraoke/lib/raspi_wifi_config.py
pikaraoke/lib/song_list.py
pikaraoke/lib/stream_manager.py
pikaraoke/lib/vlcclient.py
pikaraoke/lib/youtube_dl.py
pikaraoke/routes/admin.py
pikaraoke/routes/background_music.py
pikaraoke/routes/batch_song_renamer.py
pikaraoke/routes/controller.py
pikaraoke/routes/files.py
pikaraoke/routes/home.py
pikaraoke/routes/images.py
pikaraoke/routes/info.py
pikaraoke/routes/now_playing.py
pikaraoke/routes/preferences.py
pikaraoke/routes/queue.py
pikaraoke/routes/search.py
pikaraoke/routes/socket_events.py
pikaraoke/routes/splash.py
pikaraoke/routes/stream.py
pikaraoke/static/bulma-dark.css
pikaraoke/static/bulma.min.css
pikaraoke/static/custom.css
pikaraoke/static/fireworks.js
pikaraoke/static/hls-1.6.15.min.js
pikaraoke/static/jquery-3.7.1.min.js
pikaraoke/static/js.cookie-3.0.5.min.js
pikaraoke/static/score.css
pikaraoke/static/score.js
pikaraoke/static/screensaver.css
pikaraoke/static/screensaver.js
pikaraoke/static/selectize-0.12.6.min.js
pikaraoke/static/selectize.min.css
pikaraoke/static/socket.io-4.8.3.min.js
pikaraoke/static/spa-navigation.js
pikaraoke/static/fontello/LICENSE.txt
pikaraoke/static/fontello/README.txt
pikaraoke/static/fontello/config.json
pikaraoke/static/fontello/demo.html
pikaraoke/static/fontello/css/animation.css
pikaraoke/static/fontello/css/fontello-codes.css
pikaraoke/static/fontello/css/fontello-embedded.css
pikaraoke/static/fontello/css/fontello-ie7-codes.css
pikaraoke/static/fontello/css/fontello-ie7.css
pikaraoke-1.18.2.dist-info/METADATA
pikaraoke-1.18.2.dist-info/WHEEL
pikaraoke-1.18.2.dist-info/entry_points.txt
pikaraoke-1.18.2.dist-info/RECORD
