Metadata-Version: 2.4
Name: pikaraoke
Version: 1.18.2
Summary: Youtube-based Karaoke machine for Raspberry Pi, OSX, Windows, and Linux
Project-URL: Homepage, https://github.com/vicwomg/pikaraoke
Project-URL: Repository, https://github.com/vicwomg/pikaraoke
Author: Vic Wong
Keywords: audio,karaoke,ktv,linux,osx,raspberry-pi,video,windows,youtube
Classifier: Topic :: Games/Entertainment
Classifier: Topic :: Multimedia :: Sound/Audio
Classifier: Topic :: Multimedia :: Video
Requires-Python: >=3.10
Requires-Dist: babel==2.17.0
Requires-Dist: ffmpeg-python==0.2.0
Requires-Dist: flasgger>=0.9.5
Requires-Dist: flask-babel==4.0.0
Requires-Dist: flask-paginate==2024.4.12
Requires-Dist: flask-socketio>=5.5.0
Requires-Dist: flask==2.2.5
Requires-Dist: gevent>=24.11.1
Requires-Dist: jinja2==3.1.6
Requires-Dist: psutil==7.2.1
Requires-Dist: qrcode[png]==8.2
Requires-Dist: requests==2.32.5
Requires-Dist: yt-dlp[default]>=2026.1.29
Provides-Extra: dev
Requires-Dist: pre-commit>=3.7.1; extra == 'dev'
Requires-Dist: pytest-cov>=7.0.0; extra == 'dev'
Requires-Dist: pytest>=9.0.2; extra == 'dev'
